xboxmadeeasy/bindings.py
xboxmadeeasy/controller.py
xboxmadeeasy/state.py
xboxmadeeasy/units.py
xboxmadeeasy-0.1.0.dist-info/METADATA
xboxmadeeasy-0.1.0.dist-info/WHEEL
xboxmadeeasy-0.1.0.dist-info/top_level.txt
xboxmadeeasy-0.1.0.dist-info/RECORD
