Metadata-Version: 2.4
Name: xboxmadeeasy
Version: 0.1.0
Summary: Plug-and-play Xbox controller input tracking for Python
Author-email: Wilder <sa.yound@gmail.com>
